forgeffects/FE.py
forgeffects/FEempirical.py
forgeffects/GrafoBipartitoEncadenado.py
forgeffects/__init__.py
forgeffects/armar_caminos.py
forgeffects/directEffects.py
forgeffects/indices.py
forgeffects/iterative_maxmin_cuadrado.py
forgeffects/maxmin.py
forgeffects/process_data.py
forgeffects/process_direct_results.py
forgeffects-0.4.dist-info/LICENSE
forgeffects-0.4.dist-info/METADATA
forgeffects-0.4.dist-info/WHEEL
forgeffects-0.4.dist-info/top_level.txt
forgeffects-0.4.dist-info/RECORD
